sanddance/__init__.py
sanddance/_frontend.py
sanddance/_version.py
sanddance/sanddance.py
sanddance/labextension/msrvida-sanddance-jupyter-widget-3.1.0.tgz
sanddance/nbextension/__init__.py
sanddance/nbextension/static/extension.js
sanddance/nbextension/static/index.js
sanddance/nbextension/static/index.js.map
sanddance/tests/__init__.py
sanddance/tests/conftest.py
sanddance/tests/test_example.py
sanddance/tests/test_nbextension_path.py
sanddance-3.0.0.data/data/etc/jupyter/nbconfig/notebook.d/sanddance.json
sanddance-3.0.0.data/data/share/jupyter/lab/extensions/msrvida-sanddance-jupyter-widget-3.1.0.tgz
sanddance-3.0.0.data/data/share/jupyter/nbextensions/sanddance/extension.js
sanddance-3.0.0.data/data/share/jupyter/nbextensions/sanddance/index.js
sanddance-3.0.0.data/data/share/jupyter/nbextensions/sanddance/index.js.map
sanddance-3.0.0.dist-info/LICENSE.txt
sanddance-3.0.0.dist-info/METADATA
sanddance-3.0.0.dist-info/WHEEL
sanddance-3.0.0.dist-info/top_level.txt
sanddance-3.0.0.dist-info/RECORD
